{"assets":{"66156371223E662185B86F1487D5DCF3":{"type":"texture","index":0,"assetRequest":{"type":"slide","state":"contents","slide":"none"},"url":{"native":"assets\/BDA8F3F4-2C94-4F00-A2A8-BF03D529E0A3.pdf"},"width":1024,"height":768},"F2EBD18671E9A09EAFC02A1701AF5E90":{"type":"texture","index":1,"assetRequest":{"type":"slide","state":"contents","slide":"none"},"url":{"native":"assets\/BDA8F3F4-2C94-4F00-A2A8-BF03D529E0A3.pdf"},"width":1024,"height":768}},"events":[{"effects":[{"beginTime":0,"baseLayer":{"animations":[],"initialState":{"affineTransform":[1,0,0,1,0,0],"masksToBounds":false,"rotation":0,"scale":1,"position":{"pointX":512,"pointY":384},"width":1024,"sublayerTransform":[1,0,0,0,0,1,0,0,0,0,1,0,0,0,0,1],"contentsRect":{"y":0,"x":0,"width":1,"height":1},"opacity":1,"edgeAntialiasingMask":251658240,"height":768,"hidden":false,"anchorPoint":{"pointX":0.5,"pointY":0.5}},"objectID":"0","layers":[{"animations":[],"initialState":{"affineTransform":[1,0,0,1,0,0],"masksToBounds":false,"rotation":0,"scale":1,"position":{"pointX":512,"pointY":384},"width":1024,"sublayerTransform":[1,0,0,0,0,1,0,0,0,0,1,-0.00049229876906403734,0,0,0,1],"contentsRect":{"y":0,"x":0,"width":1,"height":1},"opacity":1,"edgeAntialiasingMask":251658240,"height":768,"hidden":false,"anchorPoint":{"pointX":0.5,"pointY":0.5}},"layers":[{"animations":[],"layers":[],"texturedRectangle":{"isBackgroundTexture":false,"singleTextureOpacity":1,"textureType":0,"textBaseline":0,"textXHeight":0,"isVerticalText":false},"initialState":{"affineTransform":[1,0,0,1,0,0],"masksToBounds":false,"rotation":0,"scale":1,"position":{"pointX":512,"pointY":384},"width":1024,"sublayerTransform":[1,0,0,0,0,1,0,0,0,0,1,0,0,0,0,1],"contentsRect":{"y":0,"x":0,"width":1,"height":1},"opacity":1,"edgeAntialiasingMask":0,"height":768,"hidden":false,"anchorPoint":{"pointX":0.5,"pointY":0.5}},"texture":"F2EBD18671E9A09EAFC02A1701AF5E90"},{"animations":[{"additive":false,"timeOffset":0,"beginTime":0,"from":{"scalar":false},"repeatCount":0,"fillMode":"both","duration":0.01,"autoreverses":false,"property":"hidden","to":{"scalar":true},"removedOnCompletion":false}],"layers":[],"texturedRectangle":{"isBackgroundTexture":false,"singleTextureOpacity":1,"textureType":0,"textBaseline":0,"textXHeight":0,"isVerticalText":false},"initialState":{"affineTransform":[1,0,0,1,0,0],"masksToBounds":false,"rotation":0,"scale":1,"position":{"pointX":512,"pointY":384},"width":1024,"sublayerTransform":[1,0,0,0,0,1,0,0,0,0,1,0,0,0,0,1],"contentsRect":{"y":0,"x":0,"width":1,"height":1},"opacity":1,"edgeAntialiasingMask":0,"height":768,"hidden":false,"anchorPoint":{"pointX":0.5,"pointY":0.5}},"texture":"66156371223E662185B86F1487D5DCF3"}]}]},"effects":[],"duration":0.01,"type":"transition","attributes":{"direction":0},"name":"none","objectID":"0"}],"automaticPlay":false,"hyperlinks":[],"accessibility":[{"text":"-7","targetRectangle":{"y":483.48002636432648,"x":686.2469482421875,"width":28.350000000000023,"height":35.160003662109375}},{"text":"Step 1. Label vertices by topological order","targetRectangle":{"y":205.32328832149506,"x":744.81973455810544,"width":230.30400000000009,"height":57.3038330078125}},{"text":"5","targetRectangle":{"y":336.9341584444046,"x":674.713623046875,"width":16.67999999999995,"height":35.160003662109375}},{"text":"2","targetRectangle":{"y":489.43302929401398,"x":304.33938598632812,"width":16.680000000000007,"height":35.160003662109375}},{"text":"1","targetRectangle":{"y":204.63891613483429,"x":572.6641845703125,"width":16.67999999999995,"height":35.160003662109375}},{"text":"START","targetRectangle":{"y":117.23466503620148,"x":383.55804443359375,"width":90.569999999999993,"height":35.160003662109375}},{"text":"-3","targetRectangle":{"y":398.50453197956085,"x":360.44107055664062,"width":28.350000000000023,"height":35.160003662109375}},{"text":"1","targetRectangle":{"y":469.00123608112335,"x":427.9075927734375,"width":16.680000000000007,"height":35.160003662109375}},{"text":"4","targetRectangle":{"y":614.07655346393585,"x":406.59295654296875,"width":16.680000000000007,"height":35.160003662109375}},{"text":"-2","targetRectangle":{"y":269.56126415729523,"x":484.95596313476562,"width":28.350000000000023,"height":35.160003662109375}},{"text":"3","targetRectangle":{"y":204.63891613483429,"x":397.22705078125,"width":16.680000000000007,"height":35.160003662109375}},{"text":"2","targetRectangle":{"y":610.86659252643585,"x":574.644775390625,"width":16.67999999999995,"height":35.160003662109375}},{"text":"6","targetRectangle":{"y":464.64268505573273,"x":572.6641845703125,"width":16.67999999999995,"height":35.160003662109375}},{"text":"Follow the DAG-based algorithm to find a shortest path from the START vertex to all other vertices in the following DAG","targetRectangle":{"y":25.707950592041016,"x":106.77562999999998,"width":818.78039999999999,"height":71.160843658447277}},{"text":"1","targetRectangle":{"y":337.69752514362335,"x":440.63427734375,"width":16.680000000000007,"height":35.160003662109375}},{"text":"4","targetRectangle":{"y":337.69752514362335,"x":293.05233764648438,"width":16.680000000000007,"height":35.160003662109375}},{"text":"4","targetRectangle":{"y":398.02421581745148,"x":609.4708251953125,"width":16.67999999999995,"height":35.160003662109375}},{"text":"2","targetRectangle":{"y":518.03627026081085,"x":503.16000366210938,"width":16.67999999999995,"height":35.160003662109375}},{"text":"5","targetRectangle":{"y":332.08439648151398,"x":539.38897705078125,"width":16.67999999999995,"height":35.160003662109375}}],"baseLayer":{"animations":[],"initialState":{"affineTransform":[1,0,0,1,0,0],"masksToBounds":false,"rotation":0,"scale":1,"position":{"pointX":512,"pointY":384},"width":1024,"sublayerTransform":[1,0,0,0,0,1,0,0,0,0,1,0,0,0,0,1],"contentsRect":{"y":0,"x":0,"width":1,"height":1},"opacity":1,"edgeAntialiasingMask":251658240,"height":768,"hidden":false,"anchorPoint":{"pointX":0.5,"pointY":0.5}},"objectID":"0","layers":[{"animations":[],"initialState":{"affineTransform":[1,0,0,1,0,0],"masksToBounds":false,"rotation":0,"scale":1,"position":{"pointX":512,"pointY":384},"width":1024,"sublayerTransform":[1,0,0,0,0,1,0,0,0,0,1,-0.00049229876906403734,0,0,0,1],"contentsRect":{"y":0,"x":0,"width":1,"height":1},"opacity":1,"edgeAntialiasingMask":251658240,"height":768,"hidden":false,"anchorPoint":{"pointX":0.5,"pointY":0.5}},"layers":[{"animations":[],"layers":[],"texturedRectangle":{"isBackgroundTexture":false,"singleTextureOpacity":1,"textureType":0,"textBaseline":0,"textXHeight":0,"isVerticalText":false},"initialState":{"affineTransform":[1,0,0,1,0,0],"masksToBounds":false,"rotation":0,"scale":1,"position":{"pointX":512,"pointY":384},"width":1024,"sublayerTransform":[1,0,0,0,0,1,0,0,0,0,1,0,0,0,0,1],"contentsRect":{"y":0,"x":0,"width":1,"height":1},"opacity":1,"edgeAntialiasingMask":0,"height":768,"hidden":false,"anchorPoint":{"pointX":0.5,"pointY":0.5}},"texture":"66156371223E662185B86F1487D5DCF3"}]}]}}]}